{
  "os":  "Linux-5.10.0-33-cloud-amd64-x86_64-with-glibc2.31",
  "python":  "3.10.15",
  "startedAt":  "2024-11-09T20:01:36.796444Z",
  "program":  "/home/shouzheyun/pizza/./code/train-main.py",
  "codePath":  "code/train-main.py",
  "git":  {
    "remote":  "https://github.com/fjzzq2002/pizza.git",
    "commit":  "4c7f2f31d215a51522b33f3ae2ef35f9c254ef6f"
  },
  "email":  "shouzheyun@gmail.com",
  "root":  "/home/shouzheyun/pizza",
  "host":  "vmimage-20241109-011527",
  "username":  "shouzheyun",
  "executable":  "/opt/conda/envs/pizza/bin/python",
  "codePathLocal":  "code/train-main.py",
  "cpu_count":  1,
  "cpu_count_logical":  2,
  "gpu":  "Tesla T4",
  "gpu_count":  1,
  "disk":  {
    "/":  {
      "total":  "211116445696",
      "used":  "39389396992"
    }
  },
  "memory":  {
    "total":  "13615443968"
  },
  "cpu":  {
    "count":  1,
    "countLogical":  2
  },
  "gpu_nvidia":  [
    {
      "name":  "Tesla T4",
      "memoryTotal":  "16106127360",
      "cudaCores":  2560,
      "architecture":  "Turing"
    }
  ],
  "cudaVersion":  "12.4"
}